Metadata-Version: 2.1
Name: dfwinreg
Version: 20240229
Summary: Digital Forensics Windows Registry (dfWinReg).
Home-page: https://github.com/log2timeline/dfwinreg
Maintainer: Log2Timeline maintainers
Maintainer-email: log2timeline-maintainers@googlegroups.com
License: Apache License, Version 2.0
Classifier: Development Status :: 3 - Alpha
Classifier: Programming Language :: Python
Requires-Python: >=3.8
License-File: ACKNOWLEDGEMENTS
License-File: AUTHORS
License-File: LICENSE
License-File: README
